moncube_modbus/__init__.py
moncube_modbus/__main__.py
moncube_modbus/constants.py
moncube_modbus/datastore.py
moncube_modbus/facade.py
moncube_modbus/utils.py
moncube_modbus/config/__init__.py
moncube_modbus/config/facade.py
moncube_modbus/config/modbus.py
moncube_modbus/config/mqtt.py
moncube_modbus/config/staleness.py
moncube_modbus/processors/__init__.py
moncube_modbus/processors/alarm_processor.py
moncube_modbus/processors/data_processor.py
moncube_modbus-1.1.0.dist-info/METADATA
moncube_modbus-1.1.0.dist-info/WHEEL
moncube_modbus-1.1.0.dist-info/entry_points.txt
moncube_modbus-1.1.0.dist-info/top_level.txt
moncube_modbus-1.1.0.dist-info/RECORD
