Metadata-Version: 2.4
Name: moncube-modbus
Version: 1.1.0
Summary: Moncube Modbus TCP Facade - Expose Moncube cubicle data via Modbus
Author: Sindika
License-Expression: MIT
Project-URL: Homepage, https://github.com/moncube/moncube-modbus
Project-URL: Documentation, https://github.com/moncube/moncube-modbus#readme
Project-URL: Repository, https://github.com/moncube/moncube-modbus
Project-URL: Bug Tracker, https://github.com/moncube/moncube-modbus/issues
Keywords: modbus,mqtt,moncube,scada,monitoring
Classifier: Development Status :: 4 - Beta
Classifier: Intended Audience :: Developers
Classifier: Programming Language :: Python :: 3
Classifier: Programming Language :: Python :: 3.8
Classifier: Programming Language :: Python :: 3.9
Classifier: Programming Language :: Python :: 3.10
Classifier: Programming Language :: Python :: 3.11
Classifier: Programming Language :: Python :: 3.12
Classifier: Topic :: System :: Monitoring
Classifier: Topic :: Software Development :: Libraries :: Python Modules
Requires-Python: >=3.8
Requires-Dist: pymodbus>=3.6.0
Requires-Dist: paho-mqtt>=2.0.0
Requires-Dist: PyYAML>=6.0
